odoo/addons/stock_quant_view_reservation/README.rst
odoo/addons/stock_quant_view_reservation/__init__.py
odoo/addons/stock_quant_view_reservation/__manifest__.py
odoo/addons/stock_quant_view_reservation/i18n/stock_quant_view_reservation.pot
odoo/addons/stock_quant_view_reservation/models/__init__.py
odoo/addons/stock_quant_view_reservation/models/stock_quant.py
odoo/addons/stock_quant_view_reservation/readme/CONTRIBUTORS.rst
odoo/addons/stock_quant_view_reservation/readme/DESCRIPTION.rst
odoo/addons/stock_quant_view_reservation/readme/USAGE.rst
odoo/addons/stock_quant_view_reservation/static/description/icon.png
odoo/addons/stock_quant_view_reservation/static/description/index.html
odoo/addons/stock_quant_view_reservation/views/stock_move_line_views.xml
odoo/addons/stock_quant_view_reservation/views/stock_quant.xml
odoo13_addon_stock_quant_view_reservation-13.0.1.0.1.dev3.dist-info/METADATA
odoo13_addon_stock_quant_view_reservation-13.0.1.0.1.dev3.dist-info/WHEEL
odoo13_addon_stock_quant_view_reservation-13.0.1.0.1.dev3.dist-info/top_level.txt
odoo13_addon_stock_quant_view_reservation-13.0.1.0.1.dev3.dist-info/RECORD
